verification/design/00_src/sra.sv
module sra (
    input  [31:0] i_operand_a, 
    input  [31:0] i_operand_b,
    output reg [31:0] o_sra_data
);

    always @(*) begin
        case (i_operand_b[4:0])
            5'd0:  o_sra_data = i_operand_a;
            5'd1:  o_sra_data = {{1{i_operand_a[31]}}, i_operand_a[31:1]};
            5'd2:  o_sra_data = {{2{i_operand_a[31]}}, i_operand_a[31:2]};
            5'd3:  o_sra_data = {{3{i_operand_a[31]}}, i_operand_a[31:3]};
            5'd4:  o_sra_data = {{4{i_operand_a[31]}}, i_operand_a[31:4]};
            5'd5:  o_sra_data = {{5{i_operand_a[31]}}, i_operand_a[31:5]};
            5'd6:  o_sra_data = {{6{i_operand_a[31]}}, i_operand_a[31:6]};
            5'd7:  o_sra_data = {{7{i_operand_a[31]}}, i_operand_a[31:7]};
            5'd8:  o_sra_data = {{8{i_operand_a[31]}}, i_operand_a[31:8]};
            5'd9:  o_sra_data = {{9{i_operand_a[31]}}, i_operand_a[31:9]};
            5'd10: o_sra_data = {{10{i_operand_a[31]}}, i_operand_a[31:10]};
            5'd11: o_sra_data = {{11{i_operand_a[31]}}, i_operand_a[31:11]};
            5'd12: o_sra_data = {{12{i_operand_a[31]}}, i_operand_a[31:12]};
            5'd13: o_sra_data = {{13{i_operand_a[31]}}, i_operand_a[31:13]};
            5'd14: o_sra_data = {{14{i_operand_a[31]}}, i_operand_a[31:14]};
            5'd15: o_sra_data = {{15{i_operand_a[31]}}, i_operand_a[31:15]};
            5'd16: o_sra_data = {{16{i_operand_a[31]}}, i_operand_a[31:16]};
            5'd17: o_sra_data = {{17{i_operand_a[31]}}, i_operand_a[31:17]};
            5'd18: o_sra_data = {{18{i_operand_a[31]}}, i_operand_a[31:18]};
            5'd19: o_sra_data = {{19{i_operand_a[31]}}, i_operand_a[31:19]};
            5'd20: o_sra_data = {{20{i_operand_a[31]}}, i_operand_a[31:20]};
            5'd21: o_sra_data = {{21{i_operand_a[31]}}, i_operand_a[31:21]};
            5'd22: o_sra_data = {{22{i_operand_a[31]}}, i_operand_a[31:22]};
            5'd23: o_sra_data = {{23{i_operand_a[31]}}, i_operand_a[31:23]};
            5'd24: o_sra_data = {{24{i_operand_a[31]}}, i_operand_a[31:24]};
            5'd25: o_sra_data = {{25{i_operand_a[31]}}, i_operand_a[31:25]};
            5'd26: o_sra_data = {{26{i_operand_a[31]}}, i_operand_a[31:26]};
            5'd27: o_sra_data = {{27{i_operand_a[31]}}, i_operand_a[31:27]};
            5'd28: o_sra_data = {{28{i_operand_a[31]}}, i_operand_a[31:28]};
            5'd29: o_sra_data = {{29{i_operand_a[31]}}, i_operand_a[31:29]};
            5'd30: o_sra_data = {{30{i_operand_a[31]}}, i_operand_a[31:30]};
            5'd31: o_sra_data = {{31{i_operand_a[31]}}, i_operand_a[31]};
            default: o_sra_data = i_operand_a;
        endcase
    end

endmodule

verification/design/00_src/srl.sv
module srl (
    input  [31:0] i_operand_a,
    input  [31:0] i_operand_b,
    output reg [31:0] o_srl_data
);

    always @(*) begin
        case (i_operand_b[4:0])
            5'd0:  o_srl_data = i_operand_a;
            5'd1:  o_srl_data = {1'b0, i_operand_a[31:1]};
            5'd2:  o_srl_data = {2'b00, i_operand_a[31:2]};
            5'd3:  o_srl_data = {3'b000, i_operand_a[31:3]};
            5'd4:  o_srl_data = {4'b0000, i_operand_a[31:4]};
            5'd5:  o_srl_data = {5'b00000, i_operand_a[31:5]};
            5'd6:  o_srl_data = {6'b000000, i_operand_a[31:6]};
            5'd7:  o_srl_data = {7'b0000000, i_operand_a[31:7]};
            5'd8:  o_srl_data = {8'b00000000, i_operand_a[31:8]};
            5'd9:  o_srl_data = {9'b000000000, i_operand_a[31:9]};
            5'd10: o_srl_data = {10'b0000000000, i_operand_a[31:10]};
            5'd11: o_srl_data = {11'b00000000000, i_operand_a[31:11]};
            5'd12: o_srl_data = {12'b000000000000, i_operand_a[31:12]};
            5'd13: o_srl_data = {13'b0000000000000, i_operand_a[31:13]};
            5'd14: o_srl_data = {14'b00000000000000, i_operand_a[31:14]};
            5'd15: o_srl_data = {15'b000000000000000, i_operand_a[31:15]};
            5'd16: o_srl_data = {16'b0000000000000000, i_operand_a[31:16]};
            5'd17: o_srl_data = {17'b00000000000000000, i_operand_a[31:17]};
            5'd18: o_srl_data = {18'b000000000000000000, i_operand_a[31:18]};
            5'd19: o_srl_data = {19'b0000000000000000000, i_operand_a[31:19]};
            5'd20: o_srl_data = {20'b00000000000000000000, i_operand_a[31:20]};
            5'd21: o_srl_data = {21'b000000000000000000000, i_operand_a[31:21]};
            5'd22: o_srl_data = {22'b0000000000000000000000, i_operand_a[31:22]};
            5'd23: o_srl_data = {23'b00000000000000000000000, i_operand_a[31:23]};
            5'd24: o_srl_data = {24'b000000000000000000000000, i_operand_a[31:24]};
            5'd25: o_srl_data = {25'b0000000000000000000000000, i_operand_a[31:25]};
            5'd26: o_srl_data = {26'b00000000000000000000000000, i_operand_a[31:26]};
            5'd27: o_srl_data = {27'b000000000000000000000000000, i_operand_a[31:27]};
            5'd28: o_srl_data = {28'b0000000000000000000000000000, i_operand_a[31:28]};
            5'd29: o_srl_data = {29'b00000000000000000000000000000, i_operand_a[31:29]};
            5'd30: o_srl_data = {30'b000000000000000000000000000000, i_operand_a[31:30]};
            5'd31: o_srl_data = {31'b0000000000000000000000000000000, i_operand_a[31]};
            default: o_srl_data = i_operand_a;
        endcase
    end

endmodule

verification/design/00_src/sll.sv
module sll (
    input  [31:0] i_operand_a,
    input  [31:0] i_operand_b,
    output reg [31:0] o_sll_data
);

    always @(*) begin
        case (i_operand_b[4:0])
            5'd0:  o_sll_data = i_operand_a;
            5'd1:  o_sll_data = {i_operand_a[30:0], 1'b0};
            5'd2:  o_sll_data = {i_operand_a[29:0], 2'b00};
            5'd3:  o_sll_data = {i_operand_a[28:0], 3'b000};
            5'd4:  o_sll_data = {i_operand_a[27:0], 4'b0000};
            5'd5:  o_sll_data = {i_operand_a[26:0], 5'b00000};
            5'd6:  o_sll_data = {i_operand_a[25:0], 6'b000000};
            5'd7:  o_sll_data = {i_operand_a[24:0], 7'b0000000};
            5'd8:  o_sll_data = {i_operand_a[23:0], 8'b00000000};
            5'd9:  o_sll_data = {i_operand_a[22:0], 9'b000000000};
            5'd10: o_sll_data = {i_operand_a[21:0], 10'b0000000000};
            5'd11: o_sll_data = {i_operand_a[20:0], 11'b00000000000};
            5'd12: o_sll_data = {i_operand_a[19:0], 12'b000000000000};
            5'd13: o_sll_data = {i_operand_a[18:0], 13'b0000000000000};
            5'd14: o_sll_data = {i_operand_a[17:0], 14'b00000000000000};
            5'd15: o_sll_data = {i_operand_a[16:0], 15'b000000000000000};
            5'd16: o_sll_data = {i_operand_a[15:0], 16'b0000000000000000};
            5'd17: o_sll_data = {i_operand_a[14:0], 17'b00000000000000000};
            5'd18: o_sll_data = {i_operand_a[13:0], 18'b000000000000000000};
            5'd19: o_sll_data = {i_operand_a[12:0], 19'b0000000000000000000};
            5'd20: o_sll_data = {i_operand_a[11:0], 20'b00000000000000000000};
            5'd21: o_sll_data = {i_operand_a[10:0], 21'b000000000000000000000};
            5'd22: o_sll_data = {i_operand_a[9:0], 22'b0000000000000000000000};
            5'd23: o_sll_data = {i_operand_a[8:0], 23'b00000000000000000000000};
            5'd24: o_sll_data = {i_operand_a[7:0], 24'b000000000000000000000000};
            5'd25: o_sll_data = {i_operand_a[6:0], 25'b0000000000000000000000000};
            5'd26: o_sll_data = {i_operand_a[5:0], 26'b00000000000000000000000000};
            5'd27: o_sll_data = {i_operand_a[4:0], 27'b000000000000000000000000000};
            5'd28: o_sll_data = {i_operand_a[3:0], 28'b0000000000000000000000000000};
            5'd29: o_sll_data = {i_operand_a[2:0], 29'b00000000000000000000000000000};
            5'd30: o_sll_data = {i_operand_a[1:0], 30'b000000000000000000000000000000};
            5'd31: o_sll_data = {i_operand_a[0],  31'b0000000000000000000000000000000};
            default: o_sll_data = i_operand_a;
        endcase
    end

endmodule

alu/src/alu.sv
module alu (
    input  [31:0] i_operand_a, i_operand_b,
    input  [3:0]  i_alu_op,
    output [31:0] o_alu_data
);
logic [31:0] temp,temp_sll,temp_srl,temp_sra;
logic [31:0] alu_temp;
logic [0:0]  carry, overflow, signed_lt, unsigned_lt;

assign {carry,temp} = i_operand_a + ~i_operand_b + 32'h1;
assign overflow     = (i_operand_a[31] ^ i_operand_b[31]) & (i_operand_a[31] ^ temp[31]);
assign signed_lt    = temp[31] ^ overflow;
assign unsigned_lt  = carry;

sll u1(
    .i_operand_a(i_operand_a),
    .i_operand_b(i_operand_b),
    .o_sll_data(temp_sll)
);
srl u2(
    .i_operand_a(i_operand_a),
    .i_operand_b(i_operand_b),
    .o_srl_data(temp_srl)
);
sra u3(
    .i_operand_a(i_operand_a),
    .i_operand_b(i_operand_b),
    .o_sra_data(temp_sra)
);

always @(*) begin
    case (i_alu_op)
        4'h0: alu_temp = i_operand_a + i_operand_b;
        4'h1: alu_temp = temp;
        4'h2: alu_temp = {31'h0, signed_lt};
        4'h3: alu_temp = {31'h0, unsigned_lt};
        4'h4: alu_temp = i_operand_a ^ i_operand_b;
        4'h5: alu_temp = i_operand_a | i_operand_b;
        4'h6: alu_temp = i_operand_a & i_operand_b;
        4'h7: alu_temp = temp_sll;
        4'h8: alu_temp = temp_srl;
        4'h9: alu_temp = temp_sra;
        4'hA: alu_temp = i_operand_b;
    default: alu_temp = 32'h00000000; 
    endcase
end

assign o_alu_data = alu_temp;
endmodule

alu/tb/alu_tb.sv
`timescale 1ns/1ps
module alu_tb ();
    logic [31:0] operand_a, operand_b;
    logic [3:0]  alu_op;
    logic [31:0] alu_data,expected_data;

    alu inst_alu(
        .i_operand_a (operand_a),
        .i_operand_b (operand_b),
        .i_alu_op    (alu_op),
        .o_alu_data  (alu_data)       
    );

    // Wave dump
    initial begin
        $dumpfile("alu_tb.vcd");
        $dumpvars(0,alu_tb);
       // #100000 $finish();
    end
    
    integer fd;
    initial begin      
        fd = $fopen("result.log","w");
    end

    integer seed = 1234;
    string op_string;

    // Simulation
    initial begin
        forever begin 
            #10 
            alu_op = $urandom_range(0, 10);
            operand_a = $random(seed);
            operand_b = (!(alu_op == 4'h7 || alu_op == 4'h8 || alu_op == 4'h9 )) ? $random(seed) : $urandom_range(0,31);
            expected_gen(operand_a,operand_b,alu_op,expected_data,op_string);
            #5
            if (!(alu_op==4'h2))
                $fdisplay(fd,"\n\nAt %0t on op %0d\na = %0d, b = %0d",$time,alu_op, operand_a, operand_b);
            else
                $fdisplay(fd,"\n\nAt %0t on op %0d\na = %0d, b = %0d",$time,alu_op, $signed(operand_a), $signed(operand_b));
            $fwrite(fd,"Result -> DUT_data = %0d, Expected_data = %0d",alu_data,expected_data);
            if (alu_data != expected_data)
                $fdisplay(fd," => ERROR on %s !!! ",op_string);
            if ($time > 10000) begin
                operand_a = 32'd4218972406;// 32'hA5FFFFFF; 
                operand_b = 32'h00000009; //9        
                alu_op = 4'h9;  //4294818868
                expected_gen(operand_a,operand_b,alu_op,expected_data,op_string);
                #5
                $display("At %0t on op %s, a = %h, b = %h, DUT_data = %h, Expected_data = %h",$time,op_string, operand_a, operand_b,alu_data,expected_data);
                operand_a = 32'd18972406;
                operand_b = -32'd32464538;       
                alu_op = 4'h2; 
                expected_gen(operand_a,operand_b,alu_op,expected_data,op_string);
                #5
                $display("At %0t on op %s, a = %0d, b = %0d, DUT_data = %0b, Expected_data = %0b",$time,op_string, $signed(operand_a), $signed(operand_b),alu_data,expected_data);
                $finish;
            end

        end
    end

    // Task
    task automatic expected_gen(input [31:0] in1, input [31:0] in2, input [3:0] op, output [31:0] out, output string s);
        case (op)
            4'h0: begin
                    out = in1 + in2;
                    s = "ADD";
            end
            4'h1: begin
                    out = in1 - in2;
                    s = "SUB";
            end
            4'h2: begin
                    out = ($signed(in1) < $signed(in2)) ? 32'h1 : 32'h0;
                    s = "SLT"; 
            end
            4'h3: begin
                    out = (in1 < in2) ? 32'h1 : 32'h0;
                    s = "SLTU"; 
            end
            4'h4: begin
                    out = in1 ^ in2;
                    s = "XOR";
            end
            4'h5: begin
                    out = in1 | in2;
                    s = "OR";
            end
            4'h6: begin
                    out = in1 & in2;
                    s = "AND";
            end
            4'h7: begin
                    out = in1 << in2[4:0];
                    s = "SLL"; 
            end
            4'h8: begin
                    out = in1 >> in2[4:0];
                     s = "SRL"; 
            end
            4'h9: begin
                    out = $signed(in1) >>> in2[4:0];
                    s = "SRA"; 
                    end
            4'hA: begin
                    out = in2;
                    s = "Operand_b"; 
            end
            default: begin
                    out = 32'b0;
                    s = "ERROR --> INVALID OP";
            end
        endcase
    endtask

endmodule

alu/sim/alu_tb.vcd
$date
	Thu Oct 10 10:27:37 2024
$end
$version
	Icarus Verilog
$end
$timescale
	1ps
$end
$scope module alu_tb $end
$var wire 32 ! alu_data [31:0] $end
$var reg 4 " alu_op [3:0] $end
$var reg 32 # expected_data [31:0] $end
$var reg 32 $ operand_a [31:0] $end
$var reg 32 % operand_b [31:0] $end
$var integer 32 & fd [31:0] $end
$var integer 32 ' seed [31:0] $end
$scope module inst_alu $end
$var wire 4 ( i_alu_op [3:0] $end
$var wire 32 ) i_operand_a [31:0] $end
$var wire 32 * i_operand_b [31:0] $end
$var wire 32 + o_alu_data [31:0] $end
$var wire 1 , overflow $end
$var wire 1 - signed_lt $end
$var wire 1 . unsigned_lt $end
$var wire 32 / temp_srl [31:0] $end
$var wire 32 0 temp_sra [31:0] $end
$var wire 32 1 temp_sll [31:0] $end
$var wire 32 2 temp [31:0] $end
$var wire 1 3 carry $end
$var reg 32 4 alu_temp [31:0] $end
$scope module u1 $end
$var wire 32 5 i_operand_a [31:0] $end
$var wire 32 6 i_operand_b [31:0] $end
$var reg 32 7 o_sll_data [31:0] $end
$upscope $end
$scope module u2 $end
$var wire 32 8 i_operand_a [31:0] $end
$var wire 32 9 i_operand_b [31:0] $end
$var reg 32 : o_srl_data [31:0] $end
$upscope $end
$scope module u3 $end
$var wire 32 ; i_operand_a [31:0] $end
$var wire 32 < i_operand_b [31:0] $end
$var reg 32 = o_sra_data [31:0] $end
$upscope $end
$upscope $end
$scope task expected_gen $end
$upscope $end
$upscope $end
$enddefinitions $end
$comment Show the parameter values. $end
$dumpall
$end
#0
$dumpvars
bx =
bx <
bx ;
bx :
bx 9
bx 8
bx 7
bx 6
bx 5
bx 4
x3
bx 2
bx 1
bx 0
bx /
x.
x-
x,
bx +
bx *
bx )
bx (
b10011010010 '
b10000000000000000000000000000011 &
bx %
bx $
bx #
bx "
bx !
$end
#10000
1-
1,
b1100010101010011110011011000110 2
0.
03
b11111000010100010100100010000000 0
b11111000010100010100100010000000 =
b1000010100010100100010000000 /
b1000010100010100100010000000 :
b1010001010010001000000010100000 1
b1010001010010001000000010100000 7
b1000000000000000 !
b1000000000000000 +
b1000000000000000 4
b1000000000000000 #
b100010011010101010000101000100 %
b100010011010101010000101000100 *
b100010011010101010000101000100 6
b100010011010101010000101000100 9
b100010011010101010000101000100 <
b10000101000101001000100000001010 $
b10000101000101001000100000001010 )
b10000101000101001000100000001010 5
b10000101000101001000100000001010 8
b10000101000101001000100000001010 ;
b10100010011010101001111101110000 '
b110 "
b110 (
#25000
0,
1.
13
b11100001110110000010010111000011 2
b10010111100011000100000000000000 1
b10010111100011000100000000000000 7
b100110001110101001 /
b100110001110101001 :
b11111111111111100110001110101001 0
b11111111111111100110001110101001 =
b1 !
b1 +
b1 4
b1 #
b10110111000100100011100001101110 %
b10110111000100100011100001101110 *
b10110111000100100011100001101110 6
b10110111000100100011100001101110 9
b10110111000100100011100001101110 <
b10011000111010100101111000110001 $
b10011000111010100101111000110001 )
b10011000111010100101111000110001 5
b10011000111010100101111000110001 8
b10011000111010100101111000110001 ;
b110111000100100011011010111110 '
b10 "
b10 (
#40000
1,
1-
b1101100101001000001010011011010 2
0.
03
b10111101000110110111111001111010 0
b10111101000110110111111001111010 =
b10111101000110110111111001111010 /
b10111101000110110111111001111010 :
b10111101000110110111111001111010 1
b10111101000110110111111001111010 7
b1101100100101110100000011010 !
b1101100100101110100000011010 +
b1101100100101110100000011010 4
b1101100100101110100000011010 #
b1010000011101110110100110100000 %
b1010000011101110110100110100000 *
b1010000011101110110100110100000 6
b1010000011101110110100110100000 9
b1010000011101110110100110100000 <
b10111101000110110111111001111010 $
b10111101000110110111111001111010 )
b10111101000110110111111001111010 5
b10111101000110110111111001111010 8
b10111101000110110111111001111010 ;
b11010000011101110110011000111100 '
b0 "
b0 (
#55000
0,
0-
b1000101001010011101011010001011 2
b11001100000100111101100110011000 1
b11001100000100111101100110011000 7
b1110011000001001111011001100110 /
b1110011000001001111011001100110 :
b11110011000001001111011001100110 0
b11110011000001001111011001100110 =
b0 !
b0 +
b0 4
b0 #
b10100000111000000001011001000001 %
b10100000111000000001011001000001 *
b10100000111000000001011001000001 6
b10100000111000000001011001000001 9
b10100000111000000001011001000001 <
b11100110000010011110110011001100 $
b11100110000010011110110011001100 )
b11100110000010011110110011001100 5
b11100110000010011110110011001100 8
b11100110000010011110110011001100 ;
b100000111000000001010101101010 '
b10 "
b10 (
#70000
0-
b1000111101111100011000010001111 2
0.
03
b100100111110001100010011001 0
b100100111110001100010011001 =
b100100111110001100010011001 /
b100100111110001100010011001 :
b10011111000110001001100100110000 1
b10011111000110001001100100110000 7
b1001011111100111101100110010111 !
b1001011111100111101100110010111 +
b1001011111100111101100110010111 4
b1001011111100111101100110010111 #
b10001100110101100100000100 %
b10001100110101100100000100 *
b10001100110101100100000100 6
b10001100110101100100000100 9
b10001100110101100100000100 <
b1001001111100011000100110010011 $
b1001001111100011000100110010011 )
b1001001111100011000100110010011 5
b1001001111100011000100110010011 8
b1001001111100011000100110010011 ;
b10000010001100110101011111001000 '
b101 "
b101 (
#85000
1-
0,
b10110110010110100111010001100110 2
b10010110100111010001101100000000 1
b10010110100111010001101100000000 7
b10110110010110100111010001 /
b10110110010110100111010001 :
b11111110110110010110100111010001 0
b11111110110110010110100111010001 =
b10110110010110100111010001 !
b10110110010110100111010001 +
b10110110010110100111010001 4
b10110110010110100111010001 #
b110 %
b110 *
b110 6
b110 9
b110 <
b10110110010110100111010001101100 $
b10110110010110100111010001101100 )
b10110110010110100111010001101100 5
b10110110010110100111010001101100 8
b10110110010110100111010001101100 ;
b110110010110100111001100101001 '
b1000 "
b1000 (
#100000
0-
0,
1.
13
b11001110001011110100000110011 2
b10001011100000 0
b10001011100000 =
b10001011100000 /
b10001011100000 :
b100111100100010000000000000000 1
b100111100100010000000000000000 7
b1001000110101011011000010001 !
b1001000110101011011000010001 +
b1001000110101011011000010001 4
b1001000110101011011000010001 #
b11110111101010100110011011101111 %
b11110111101010100110011011101111 *
b11110111101010100110011011101111 6
b11110111101010100110011011101111 9
b11110111101010100110011011101111 <
b10001011100000100111100100010 $
b10001011100000100111100100010 )
b10001011100000100111100100010 5
b10001011100000100111100100010 8
b10001011100000100111100100010 ;
b1110111101010100110010101011111 '
b0 "
b0 (
#115000
1-
b11101110010010101110101111011100 2
b11111111110000000001110111111000 1
b11111111110000000001110111111000 7
b1011111111110000000001110111 /
b1011111111110000000001110111 :
b1011111111110000000001110111 0
b1011111111110000000001110111 =
b1111111111111010001011111111111 !
b1111111111111010001011111111111 +
b1111111111111010001011111111111 4
b1111111111111010001011111111111 #
b1110001101011010001011111100011 %
b1110001101011010001011111100011 *
b1110001101011010001011111100011 6
b1110001101011010001011111100011 9
b1110001101011010001011111100011 <
b1011111111110000000001110111111 $
b1011111111110000000001110111111 )
b1011111111110000000001110111111 5
b1011111111110000000001110111111 8
b1011111111110000000001110111111 ;
b11110001101011010001010000000101 '
b101 "
b101 (
#130000
1,
1-
b1111011111101101011011011111000 2
0.
03
b11111111111111111111110010110100 0
b11111111111111111111110010110100 =
b1110010110100 /
b1110010110100 :
b1010110010110000000000000000000 1
b1010110010110000000000000000000 7
b11101101101010111101101111011011 !
b11101101101010111101101111011011 +
b11101101101010111101101111011011 4
b11101101101010111101101111011011 #
b1101001101010111001001111010011 %
b1101001101010111001001111010011 *
b1101001101010111001001111010011 6
b1101001101010111001001111010011 9
b1101001101010111001001111010011 <
b11100101101000100100101011001011 $
b11100101101000100100101011001011 )
b11100101101000100100101011001011 5
b11100101101000100100101011001011 8
b11100101101000100100101011001011 ;
b11101001101010111001000010011011 '
#145000
0,
1-
b11100101010101011010110010110111 2
b1100110010100000000000000000000 1
b1100110010100000000000000000000 7
b1110010101010 /
b1110010101010 :
b11111111111111111111110010101010 0
b11111111111111111111110010101010 =
b1110010101010 !
b1110010101010 +
b1110010101010 4
b1110010101010 #
b10011 %
b10011 *
b10011 6
b10011 9
b10011 <
b11100101010101011010110011001010 $
b11100101010101011010110011001010 )
b11100101010101011010110011001010 5
b11100101010101011010110011001010 8
b11100101010101011010110011001010 ;
b1100101010101011010101100100000 '
b1000 "
b1000 (
#160000
0-
b11111110100000111010000111111 2
b11111111111111111111110101010011 0
b11111111111111111111110101010011 =
b10101010011 /
b10101010011 :
b1001010100000000000000000000000 1
b1001010100000000000000000000000 7
b10001010100110100011011000010101 !
b10001010100110100011011000010101 +
b10001010100110100011011000010101 4
b10001010100110100011011000010101 #
b10001010100110100011011000010101 %
b10001010100110100011011000010101 *
b10001010100110100011011000010101 6
b10001010100110100011011000010101 9
b10001010100110100011011000010101 <
b10101010011010101010101001010100 $
b10101010011010101010101001010100 )
b10101010011010101010101001010100 5
b10101010011010101010101001010100 8
b10101010011010101010101001010100 ;
b1010100110100011010111101110 '
b1010 "
b1010 (
#175000
b1000001010000100011011110001 2
0.
03
b0 1
b0 7
b0 /
b0 :
b0 0
b0 =
b0 !
b0 +
b0 4
b0 #
b11111 %
b11111 *
b11111 6
b11111 9
b11111 <
b1000001010000100011100010000 $
b1000001010000100011100010000 )
b1000001010000100011100010000 5
b1000001010000100011100010000 8
b1000001010000100011100010000 ;
b10001000001010000100010110010111 '
b1000 "
b1000 (
#190000
1-
0,
b10001010111011111001011100010110 2
b11111111111111111111111111111101 0
b11111111111111111111111111111101 =
b1101 /
b1101 :
b100000000000000000000000000000 1
b100000000000000000000000000000 7
b10010111001100001010100100101110 !
b10010111001100001010100100101110 +
b10010111001100001010100100101110 4
b10010111001100001010100100101110 #
b1001110011011111100111110011100 %
b1001110011011111100111110011100 *
b1001110011011111100111110011100 6
b1001110011011111100111110011100 9
b1001110011011111100111110011100 <
b11011001010111110110011010110010 $
b11011001010111110110011010110010 )
b11011001010111110110011010110010 5
b11011001010111110110011010110010 8
b11011001010111110110011010110010 ;
b11001110011011111100110011111101 '
b100 "
b100 (
#205000
0-
b1110100011110111111000011101 2
0.
03
b1100100110000000000000000000000 1
b1100100110000000000000000000000 7
b100100111 /
b100100111 :
b100100111 0
b100100111 =
b1110010101100001000001011100101 !
b1110010101100001000001011100101 +
b1110010101100001000001011100101 4
b1110010101100001000001011100101 #
b111011010111011000001101110110 %
b111011010111011000001101110110 *
b111011010111011000001101110110 6
b111011010111011000001101110110 9
b111011010111011000001101110110 <
b1001001111011010000000110010011 $
b1001001111011010000000110010011 )
b1001001111011010000000110010011 5
b1001001111011010000000110010011 8
b1001001111011010000000110010011 ;
b10111011010111011000000001010011 '
#220000
1-
1.
13
b11111110000011100001101111111100 2
b11111111111111111111111110010011 0
b11111111111111111111111110010011 =
b110010011 /
b110010011 :
b1001001100000000000000000000000 1
b1001001100000000000000000000000 7
b1 !
b1 +
b1 4
b1 #
b11001011101010001101111010010111 %
b11001011101010001101111010010111 *
b11001011101010001101111010010111 6
b11001011101010001101111010010111 9
b11001011101010001101111010010111 <
b11001001101101101111101010010011 $
b11001001101101101111101010010011 )
b11001001101101101111101010010011 5
b11001001101101101111101010010011 8
b11001001101101101111101010010011 ;
b1001011101010001101110100011001 '
b11 "
b11 (
#235000
1,
1-
0.
03
b1010101111111100101010010101100 2
b1101000110001010100000011010 1
b1101000110001010100000011010 7
b1000011010001100010101000000110 /
b1000011010001100010101000000110 :
b11000011010001100010101000000110 0
b11000011010001100010101000000110 =
b110000100011011111111101100001 !
b110000100011011111111101100001 +
b110000100011011111111101100001 4
b110000100011011111111101100001 #
b110000100011011111111101100001 %
b110000100011011111111101100001 *
b110000100011011111111101100001 6
b110000100011011111111101100001 9
b110000100011011111111101100001 <
b10000110100011000101010000001101 $
b10000110100011000101010000001101 )
b10000110100011000101010000001101 5
b10000110100011000101010000001101 8
b10000110100011000101010000001101 ;
b10110000100011011111110011001111 '
b1010 "
b1010 (
#250000
0-
0,
b1001111111010110000000010100000 2
1.
13
b101000101100011110111 0
b101000101100011110111 =
b101000101100011110111 /
b101000101100011110111 :
b1011000111101110010100000000000 1
b1011000111101110010100000000000 7
b0 !
b0 +
b0 4
b0 #
b11000100011011011111011010001000 %
b11000100011011011111011010001000 *
b11000100011011011111011010001000 6
b11000100011011011111011010001000 9
b11000100011011011111011010001000 <
b10100010110001111011100101000 $
b10100010110001111011100101000 )
b10100010110001111011100101000 5
b10100010110001111011100101000 8
b10100010110001111011100101000 ;
b1000100011011011111010011110101 '
b10 "
b10 (
#265000
1-
0,
b10110001101101000110000101100011 2
0.
03
b11100101001101010101100000000000 1
b11100101001101010101100000000000 7
b11010110011100101001101 /
b11010110011100101001101 :
b11111111111010110011100101001101 0
b11111111111010110011100101001101 =
b11111011001100001101001111110101 !
b11111011001100001101001111110101 +
b11111011001100001101001111110101 4
b11111011001100001101001111110101 #
b100100101111100011100101001001 %
b100100101111100011100101001001 *
b100100101111100011100101001001 6
b100100101111100011100101001001 9
b100100101111100011100101001001 <
b11010110011100101001101010101100 $
b11010110011100101001101010101100 )
b11010110011100101001101010101100 5
b11010110011100101001101010101100 8
b11010110011100101001101010101100 ;
b10100100101111100011011100001011 '
b0 "
b0 (
#280000
0-
b1001100001010001010010101111001 2
b0 0
b0 =
b0 /
b0 :
b0 1
b0 7
b0 !
b0 +
b0 4
b0 #
b11111 %
b11111 *
b11111 6
b11111 9
b11111 <
b1001100001010001010010110011000 $
b1001100001010001010010110011000 )
b1001100001010001010010110011000 5
b1001100001010001010010110011000 8
b1001100001010001010010110011000 ;
b11001100001010001010001011010000 '
b1000 "
b1000 (
#295000
0-
b1010100011111111000000010101 2
b1111011110010010111110000000000 1
b1111011110010010111110000000000 7
b1010111110011110111100 /
b1010111110011110111100 :
b11111111111010111110011110111100 0
b11111111111010111110011110111100 =
b1010100100011111000000010101 !
b1010100100011111000000010101 +
b1010100100011111000000010101 4
b1010100100011111000000010101 #
b10100101000011110000001001001010 %
b10100101000011110000001001001010 *
b10100101000011110000001001001010 6
b10100101000011110000001001001010 9
b10100101000011110000001001001010 <
b10101111100111101111001001011111 $
b10101111100111101111001001011111 )
b10101111100111101111001001011111 5
b10101111100111101111001001011111 8
b10101111100111101111001001011111 ;
b100101000011110000000100011110 '
b100 "
b100 (
#310000
1-
0,
b11101100111101000101101111011010 2
b11111111111100010011000001101100 0
b11111111111100010011000001101100 =
b111100010011000001101100 /
b111100010011000001101100 :
b110000011011001110001000000000 1
b110000011011001110001000000000 7
b11110101000011000111110111101010 !
b11110101000011000111110111101010 +
b11110101000011000111110111101010 4
b11110101000011000111110111101010 #
b100001111000001000100001000 %
b100001111000001000100001000 *
b100001111000001000100001000 6
b100001111000001000100001000 9
b100001111000001000100001000 <
b11110001001100000110110011100010 $
b11110001001100000110110011100010 )
b11110001001100000110110011100010 5
b11110001001100000110110011100010 8
b11110001001100000110110011100010 ;
b10000100001111000000111110011100 '
#325000
1-
1.
13
b10110110000011011111010101101100 2
b11000000000000000000000000000000 1
b11000000000000000000000000000000 7
b100000000111 /
b100000000111 :
b11111111111111111111100000000111 0
b11111111111111111111100000000111 =
b1001010000011100001101010010100 !
b1001010000011100001101010010100 +
b1001010000011100001101010010100 4
b1001010000011100001101010010100 #
b11001010011100010111011010010100 %
b11001010011100010111011010010100 *
b11001010011100010111011010010100 6
b11001010011100010111011010010100 9
b11001010011100010111011010010100 <
b10000000011111110110110000000000 $
b10000000011111110110110000000000 )
b10000000011111110110110000000000 5
b10000000011111110110110000000000 8
b10000000011111110110110000000000 ;
b1001010011100010111010111001010 '
#340000
0-
0.
03
b1010101101000001001011110100000 2
b10101011010000010010 0
b10101011010000010010 =
b10101011010000010010 /
b10101011010000010010 :
b100101111010101100000000000 1
b100101111010101100000000000 7
b100101111010101100000000000 !
b100101111010101100000000000 +
b100101111010101100000000000 4
b100101111010101100000000000 #
b1011 %
b1011 *
b1011 6
b1011 9
b1011 <
b1010101101000001001011110101011 $
b1010101101000001001011110101011 )
b1010101101000001001011110101011 5
b1010101101000001001011110101011 8
b1010101101000001001011110101011 ;
b11010101101000001001010011000011 '
b111 "
b111 (
#355000
b11011100101010100010000110111 2
b11011110100000001001100110110000 1
b11011110100000001001100110110000 7
b100110111101000000010011001 /
b100110111101000000010011001 :
b100110111101000000010011001 0
b100110111101000000010011001 =
b10000000001110101100111011111111 !
b10000000001110101100111011111111 +
b10000000001110101100111011111111 4
b10000000001110101100111011111111 #
b110010010100101100010101100100 %
b110010010100101100010101100100 *
b110010010100101100010101100100 6
b110010010100101100010101100100 9
b110010010100101100010101100100 <
b1001101111010000000100110011011 $
b1001101111010000000100110011011 )
b1001101111010000000100110011011 5
b1001101111010000000100110011011 8
b1001101111010000000100110011011 ;
b10110010010100101100001100001001 '
b0 "
b0 (
