brcomp/src/brcomp.sv
module brcomp (
    input  [31:0] rs1_data, rs2_data,
    input  [0:0]  br_unsigned,
    output [0:0]  br_less, br_equal
);
    logic [31:0] sub;
    logic overflow, carry;
    logic [0:0] br_equal_reg, br_less_reg;
    assign {carry,sub} = rs1_data + ~rs2_data + 32'b1;
    assign overflow = (rs1_data[31] ^ rs2_data[31]) & (rs1_data[31] ^ sub[31]); 

    always @(*) begin
        if (br_unsigned) begin
            br_less_reg = carry;
            br_equal_reg = (!sub) ? 1 : 0;
        end else begin
            br_less_reg = sub[31] ^ overflow;
            br_equal_reg = (!sub) ? 1 : 0;
        end
    end

    assign br_less = br_less_reg;
    assign br_equal = br_equal_reg;
endmodule

brcomp/tb/tb.sv
`timescale 1ns/1ps
module tb ();
    logic  [31:0] rs1_data, rs2_data;
    logic  [0:0]  br_unsigned;
    logic  [0:0]  br_less, br_equal;

    brcomp inst_brcomp(
        .rs1_data    (rs1_data),
        .rs2_data    (rs2_data),
        .br_unsigned (br_unsigned),
        .br_less     (br_less),
        .br_equal    (br_equal)  
    );

    // Wave dump
    initial begin
        $dumpfile("tb.vcd");
        $dumpvars(0,tb);
        #1000 $finish();
    end

    integer seed1, seed2;

    initial begin
        seed1 = 12;
        seed2 = 6;
        #5
        rs1_data = $random(seed1);
        rs2_data = $random(seed2);
        br_unsigned = $urandom_range(0,1);
        if (br_unsigned) begin
            if (!(br_equal == (rs1_data == rs2_data))) $display("Error in unsigned equal");
            else if (!(br_less == (rs1_data < rs2_data))) $display("Error in unsigned less than");
        end else begin
            if (!(br_equal == ($signed(rs1_data) == $signed(rs2_data)))) $display("Error in signed equal");
            else if (!(br_less == ($signed(rs1_data) < $signed(rs2_data)))) $display("Error in signed less than");
        end
    end
endmodule

brcomp/sim/tb.vcd
$date
	Wed Nov 13 15:19:42 2024
$end
$version
	Icarus Verilog
$end
$timescale
	1ps
$end
$scope module tb $end
$var wire 1 ! br_less $end
$var wire 1 " br_equal $end
$var reg 1 # br_unsigned $end
$var reg 32 $ rs1_data [31:0] $end
$var reg 32 % rs2_data [31:0] $end
$var integer 32 & seed1 [31:0] $end
$var integer 32 ' seed2 [31:0] $end
$scope module inst_brcomp $end
$var wire 1 " br_equal $end
$var wire 1 ! br_less $end
$var wire 1 # br_unsigned $end
$var wire 1 ( overflow $end
$var wire 32 ) rs1_data [31:0] $end
$var wire 32 * rs2_data [31:0] $end
$var wire 32 + sub [31:0] $end
$var wire 1 , carry $end
$var reg 1 - br_equal_reg $end
$var reg 1 . br_less_reg $end
$upscope $end
$upscope $end
$enddefinitions $end
$comment Show the parameter values. $end
$dumpall
$end
#0
$dumpvars
x.
x-
x,
bx +
bx *
bx )
x(
b110 '
b1100 &
bx %
bx $
x#
x"
x!
$end
#5000
0"
0-
1!
1.
0(
b1100101001000000000 +
0,
1#
b10000000000001100101010000000000 %
b10000000000001100101010000000000 *
b1100101001011001111 '
b10000000000011001010011000000000 $
b10000000000011001010011000000000 )
b11001010010110011101 &
#10000
0(
1!
1.
b10101010000100101100001101010100 +
0#
b101010000100111101010101010100 %
b101010000100111101010101010100 *
b10101010000100111101001011000100 '
b11010100001001101001100010101000 $
b11010100001001101001100010101000 )
b1010100001001101001011110111010 &
#15000
1(
1,
0!
0.
b11101001111111100011011111010100 +
b10000110010101111011110000001100 %
b10000110010101111011110000001100 *
b110010101111011101011110101 '
b1110000010101011111001111100000 $
b1110000010101011111001111100000 )
b11110000010101011111000111110011 &
#20000
b10000000010110101111000100000001 +
b11000011101101000010100010000111 %
b11000011101101000010100010000111 *
b1000011101101000010011100110010 '
b1000100000011110001100110001000 $
b1000100000011110001100110001000 )
b11000100000011110001011010011000 &
#25000
1!
1.
0(
0,
b1010110010111111110001010101101 +
1#
b100011100101110111100001000 %
b100011100101110111100001000 *
b10000100011100101110110100001011 '
b1011010110100101101000110110101 $
b1011010110100101101000110110101 )
b11011010110100101100111110111001 &
#30000
0!
0.
1,
b11101011111110010101101111011000 +
b1010011000111000110001110100110 %
b1010011000111000110001110100110 *
b11010011000111000110000011010000 '
b111111000101011011111101111110 $
b111111000101011011111101111110 )
b10111111000101011011110000100110 &
#35000
1!
1.
b11111011101001111000000111111000 +
1,
0#
b1011111011101000001100110111110 %
b1011111011101000001100110111110 *
b11011111011101000001011010010001 '
b1011011000110111001101110110110 $
b1011011000110111001101110110110 )
b11011011000110111001100001101111 &
#40000
b10001000100110010100001100010001 +
0,
b1101011101011000111000111010111 %
b1101011101011000111000111010111 *
b11101011101011000110111100011110 '
b11110100010001011011010011101000 $
b11110100010001011011010011101000 )
b1110100010001011011001111100100 &
#45000
1(
b1110000000000000001111011100000 +
1#
b1101001110101111000001111010011 %
b1101001110101111000001111010011 *
b11101001110101111000000100000111 '
b11011001110101111010001010110011 $
b11011001110101111010001010110011 )
b1011001110101111010000110010101 &
#50000
0(
0!
0.
b11010010010011110100011110100100 +
1,
b110100001001101010111101101000 %
b110100001001101010111101101000 *
b10110100001001101010110110011100 '
b110011101011111011100001100 $
b110011101011111011100001100 )
b10000110011101011111010101010010 &
#55000
b10110111110101101010101101110000 +
b1100111011001011111001111001110 %
b1100111011001011111001111001110 *
b11100111011001011111000111101101 '
b11111001111001001111100111110 $
b11111001111001001111100111110 )
b10011111001111001001110010101011 &
#60000
0!
0.
b11001000010100000101111110010001 +
1,
b11101011110110001100010011010111 %
b11101011110110001100010011010111 *
b1101011110110001100001111001010 '
b10110100001010010010010001101000 $
b10110100001010010010010001101000 )
b110100001010010010001111110000 &
#65000
1(
b11011101011001001110110110111011 +
b10100010010100000000110001000100 %
b10100010010100000000110001000100 *
b100010010100000000101011000011 '
b1111111101101001111100111111111 $
b1111111101101001111100111111111 )
b11111111101101001111011100110001 &
#70000
1!
1.
0(
0,
b1010110010000001110101010101101 +
b10101011001111000011100101010 %
b10101011001111000011100101010 *
b10010101011001111000010100101000 '
b1101011101010000111000111010111 $
b1101011101010000111000111010111 )
b11101011101010000110111100111110 &
#75000
0!
0.
1,
b1000111111101001001001010010000 +
b11101010110100001010101011010101 %
b11101010110100001010101011010101 *
b1101010110100001010100100001001 '
b110010110001010011110101100101 $
b110010110001010011110101100101 )
b10110010110001010011101010100111 &
#80000
0(
0,
1!
1.
b10011011110110111010000100111000 +
0#
b1001010101101011101001110010101 %
b1001010101101011101001110010101 *
b11001010101101011101000100110110 '
b11100110100100010111010011001101 $
b11100110100100010111010011001101 )
b1100110100100010111001010111100 &
#85000
1(
1,
0!
0.
b10010111100110100010011100110000 +
b11100000011011100100100011000000 %
b11100000011011100100100011000000 *
b1100000011011100100011000111111 '
b1111000000010000110111111110000 $
b1111000000010000110111111110000 )
b11111000000010000110110010001101 &
#90000
0(
0!
0.
b1100000101100001010001011000001 +
0,
b10011000000111100111010000110000 %
b10011000000111100111010000110000 *
b11000000111100111001101110100 '
b11111000110011110001011011110001 $
b11111000110011110001011011110001 )
b1111000110011110001010111101010 &
#95000
1!
1.
b1000001010000001100000010000 +
1#
b11001111101100110101100010011111 %
b11001111101100110101100010011111 *
b1001111101100110101011111100101 '
b11010111110110110111000010101111 $
b11010111110110110111000010101111 )
b1010111110110110110111001100011 &
#100000
0!
0.
1(
b10100111101111000110101101010000 +
1,
0#
b11000101111110010000010010001011 %
b11000101111110010000010010001011 *
b1000101111110010000001101100010 '
b1101101101101010110111111011011 $
b1101101101101010110111111011011 )
b11101101101101010110110001001000 &
#105000
0(
0,
b1001100000110011010111010011001 +
b110000111101011011000101100001 %
b110000111101011011000101100001 *
b10110000111101011010111101111011 '
b1111101000011110101111111111010 $
b1111101000011110101111111111010 )
b11111101000011110101110110101001 &
#110000
1,
0!
0.
b11101100100101101100111111011001 +
1#
b1011110001000011100011110111100 %
b1011110001000011100011110111100 *
b11011110001000011100010010000000 '
b1001010101110001001011110010101 $
b1001010101110001001011110010101 )
b11001010101110001001010101010110 &
#115000
0!
0.
b11101110001101100001011111011100 +
1,
b11011100100001001101110010111001 %
b11011100100001001101110010111001 *
b1011100100001001101101010000001 '
b11001010101110101111010010010101 $
b11001010101110101111010010010101 )
b1001010101110101111001111011111 &
#120000
0,
1!
1.
b10011001111110100001010100110100 +
0#
b101111111111001000100101011111 %
b101111111111001000100101011111 *
b10101111111111001000011001001110 '
b11001001111101101001111010010011 $
b11001001111101101001111010010011 )
b1001001111101101001110010010100 &
#125000
0!
0.
b10110101010110110010000101110 +
b11000110010101111000010010001100 %
b11000110010101111000010010001100 *
b1000110010101111000001001110111 '
b11011101000000101110100010111010 $
b11011101000000101110100010111010 )
b1011101000000101110011010000101 &
#130000
b111111011000011101010001111111 +
1,
b11001000001010101000011010010000 %
b11001000001010101000011010010000 *
b1001000001010101000010001001100 '
b111100011000101101100001111 $
b111100011000101101100001111 )
b10000111100011000101100110000010 &
#135000
b10001110011000010111100100011100 +
1#
b11110111000011111100111011101110 %
b11110111000011111100111011101110 *
b1110111000011111100110011011101 '
b10000101011100010100100000001010 $
b10000101011100010100100000001010 )
b101011100010100011100011011 &
#140000
1(
0,
1!
1.
b1110001100000100000100011100011 +
0#
b1110001111010110100011111100011 %
b1110001111010110100011111100011 *
b11110001111010110100010111111010 '
b11100011011011010101000011000110 $
b11100011011011010101000011000110 )
b1100011011011010100111110100000 &
#145000
0(
1!
1.
b10001001010001010010011100010011 +
b1110001111011101011110111100011 %
b1110001111011101011110111100011 *
b11110001111011101011101100110011 '
b11111011001100111110010011110110 $
b11111011001100111110010011110110 )
b1111011001100111110001100100001 &
#150000
0(
1!
1.
b10010111010101100000111100101111 +
b10110111000001000000100101101 %
b10110111000001000000100101101 *
b10010110111000000111111011011000 '
b10101110001101101001000001011100 $
b10101110001101101001000001011100 )
b101110001101101000111001101110 &
#155000
b10011110010010110001100100111100 +
b110111000011101000110101101110 %
b110111000011101000110101101110 *
b10110111000011101000101011111001 '
b11010101010110011010011010101010 $
b11010101010110011010011010101010 )
b1010101010110011010010000010111 &
#160000
0!
0.
b10101011100001111010000101010111 +
1,
1#
b1011110101011001111000110111101 %
b1011110101011001111000110111101 *
b11011110101011001110111001100110 '
b1010001101001001001100010100 $
b1010001101001001001100010100 )
b10001010001101001001000101101100 &
#165000
1(
0!
0.
b11100001111010101101101111000100 +
1,
0#
b10000110111111000001011000001101 %
b10000110111111000001011000001101 *
b110111111000001010110101111 '
b1101000111001101111000111010001 $
b1101000111001101111000111010001 )
b11101000111001101110111101111101 &
#170000
0(
0!
0.
b10101111111011011101111101100000 +
1,
1#
b11111010101001100100001011110101 %
b11111010101001100100001011110101 *
b1111010101001100100000000100100 '
b10101010100101000010001001010101 $
b10101010100101000010001001010101 )
b101010100101000010000000011010 &
#175000
b11010101110100011101010110101011 +
b1101000100001110011001111010001 %
b1101000100001110011001111010001 *
b11101000100001110011000011010101 '
b111110010110010000100101111100 $
b111110010110010000100101111100 )
b10111110010110010000011011010011 &
#180000
1(
0!
0.
b10110110111001000100001101101101 +
1,
0#
b11000010100100011110110010000101 %
b11000010100100011110110010000101 *
b1000010100100011110101110010010 '
b1111001011101100010111111110010 $
b1111001011101100010111111110010 )
b11111001011101100010110111111000 &
#185000
0(
0,
b1001110100011100101101010011101 +
b100011011000100000111101000110 %
b100011011000100000111101000110 *
b10100011011000100000110111101011 '
b1110001111100000110100111100011 $
b1110001111100000110100111100011 )
b11110001111100000110011110011001 &
#190000
1(
1!
1.
b1111100001110011010010011111000 +
b1011110001001010001011110111100 %
b1011110001001010001011110111100 *
b11011110001001010001010000110000 '
b11011010010111101011110010110100 $
b11011010010111101011110010110100 )
b1011010010111101011101010000110 &
#195000
0!
0.
0(
b1101111100101001000000011100 +
b1011001111001111001110110110011 %
b1011001111001111001110110110011 *
b11011001111001111001101001110001 '
b1100111110110100010110111001111 $
b1100111110110100010110111001111 )
b11100111110110100010101101001111 &
#200000
b1101011101110100100000011011 +
b1011011101111110110101110110111 %
b1011011101111110110101110110111 *
b11011011101111110110100101111110 '
b1101001001101101011001111010010 $
b1101001001101101011001111010010 )
b11101001001101101011000101000100 &
#205000
1!
1.
b11110111011111000100000111110 +
1#
b10011010001000001110000000110100 %
b10011010001000001110000000110100 *
b11010001000001101111111100111 '
b10111001000100000110100001110010 $
b10111001000100000110100001110010 )
b111001000100000110011101110101 &
#210000
0(
0!
0.
b1110111001111111100001011101110 +
1,
0#
b11110111100110010000100011101111 %
b11110111100110010000100011101111 *
b1110111100110010000011011111100 '
b1101110110110001100101111011101 $
b1101110110110001100101111011101 )
b11101110110110001100100110110010 &
#215000
1(
0,
1!
1.
b1111101101010000010100011111100 +
b10001111000010110010100100011 %
b10001111000010110010100100011 *
b10010001111000010110001111001101 '
b10001111100010011000111000011111 $
b10001111100010011000111000011111 )
b1111100010011000110110001011 &
#220000
0!
0.
0(
b1010011100001100001001010100111 +
b100111010110110101011101001110 %
b100111010110110101011101001110 *
b10100111010110110101010000101010 '
b1111010111000010110100111110101 $
b1111010111000010110100111110101 )
b11111010111000010110011101010000 &
#225000
1,
0!
0.
b11000100011111000100001110001001 +
1#
b1111011100100101000100111110111 %
b1111011100100101000100111110111 *
b11111011100100101000011110100011 '
b1000000000011101100110110000000 $
b1000000000011101100110110000000 )
b11000000000011101100101100010001 &
#230000
1!
1.
b11101010010111001001001111010101 +
1,
0#
b11101100110111001110011011011001 %
b11101100110111001110011011011001 *
b1101100110111001110010010001000 '
b11010111001110010111101010101110 $
b11010111001110010111101010101110 )
b1010111001110010111100110011110 &
#235000
0!
0.
b11110100110010110111111111101001 +
1#
b11001001000001011110101010010010 %
b11001001000001011110101010010010 *
b1001001000001011110100011101001 '
b10111101110100010110101001111011 $
b10111101110100010110101001111011 )
b111101110100010110100110000111 &
#240000
b11011101000111000000010110111011 +
b101111011110000101100101011110 %
b101111011110000101100101011110 *
b10101111011110000101011110010110 '
b1100100101000101111100011001 $
b1100100101000101111100011001 )
b10001100100101000101110000011100 &
#245000
1!
1.
b10000000001100000110110100000001 +
0,
0#
b1110111011001101100001111101110 %
b1110111011001101100001111101110 *
b11110111011001101100000100011111 '
b11110111100101110011000011101111 $
b11110111100101110011000011101111 )
b1110111100101110010111001101101 &
#250000
0!
0.
1(
b10001001101000100111111100010011 +
1,
b10010110001101100011101000101100 %
b10010110001101100011101000101100 *
b10110001101100011100011010100 '
b11111110110001011100100111111 $
b11111110110001011100100111111 )
b10011111110110001011011001001010 &
#255000
0(
b11110100111100110111010111101010 +
1#
b1000011001000100100011110000110 %
b1000011001000100100011110000110 *
b11000011001000100100010111000101 '
b111000000101011011110101110000 $
b111000000101011011110101110000 )
b10111000000101011011101101000011 &
#260000
0!
0.
b11111001011010100111101111110011 +
1,
b11000101110000011110000010001011 %
b11000101110000011110000010001011 *
b1000101110000011101111111000010 '
b10111111001011000101110001111110 $
b10111111001011000101110001111110 )
b111111001011000101101110101000 &
#265000
1!
1.
0,
b10011110011101011110001100111101 +
b10100010111110000101100101000 %
b10100010111110000101100101000 *
b10010100010111110000100001011011 '
b10110010110101001110111001100101 $
b10110010110101001110111001100101 )
b110010110101001110110110001001 &
#270000
b11000110001110011101101110001101 +
0#
b101011111000010101000101010111 %
b101011111000010101000101010111 *
b10101011111000010100111111100000 '
b11110010000110110010110011100100 $
b11110010000110110010110011100100 )
b1110010000110110010101110110110 &
#275000
0!
0.
1(
1,
b10001000010101001110100100010001 +
1#
b11100100010110110101100011001000 %
b11100100010110110101100011001000 *
b1100100010110110101011001100001 '
b1101100101100000100000111011001 $
b1101100101100000100000111011001 )
b11101100101100000011111010111111 &
#280000
0(
0!
0.
b1100100001010001101100011001001 +
0#
b11010110111010000001101010101101 %
b11010110111010000001101010101101 *
b1010110111010000001100010101110 '
b111011000100001111001101110110 $
b111011000100001111001101110110 )
b10111011000100001111000111110100 &
#285000
b100001000001001000110001000010 +
1#
b11111001110010101001101011110011 %
b11111001110010101001101011110011 *
b1111001110010101001100101010111 '
b11010110011110010011100110101 $
b11010110011110010011100110101 )
b10011010110011110010010001100101 &
#290000
b110110110000010001000001101110 +
b11101010010111010011011011010100 %
b11101010010111010011011011010100 *
b1101010010111010011010110101100 '
b100001000111100100011101000010 $
b100001000111100100011101000010 )
b10100001000111100100010111100010 &
#295000
1(
b10110110101000101011100101101101 +
b10011110000010011011100000111100 %
b10011110000010011011100000111100 *
b11110000010011011011010111101 '
b1010100101011000111000110101001 $
b1010100101011000111000110101001 )
b11010100101011000110111111111011 &
#300000
0(
1!
1.
b111100111101000111110001111010 +
0,
b11000010110010111111000010000101 %
b11000010110010111111000010000101 *
b1000010110010111110111001011010 '
b11111111110000000110110011111111 $
b11111111110000000110110011111111 )
b1111111110000000110101100000000 &
#305000
0(
1!
1.
b10110110110000100011110101101110 +
0#
b1000110110000100111001110001101 %
b1000110110000100111001110001101 *
b11000110110000100111000000010011 '
b11111101100001001011000011111011 $
b11111101100001001011000011111011 )
b1111101100001001010111100000001 &
#310000
0!
0.
0(
1,
b1110101101011000111101011101100 +
1#
b11111001011101111011100011110010 %
b11111001011101111011100011110010 *
b1111001011101111011011000111000 '
b1101111001001000011001111011110 $
b1101111001001000011001111011110 )
b11101111001001000011000011001110 &
#315000
b1110111111011011100100011110000 +
0#
b10001111010101011100010000011110 %
b10001111010101011100010000011110 *
b1111010101011100001011011001 '
b111010000111000110100001110 $
b111010000111000110100001110 )
b10000111010000111000101011110111 &
#320000
1!
1.
b11100100101100001100010111001010 +
1,
b11100101011010110000111011001010 %
b11100101011010110000111011001010 *
b1100101011010110000110011000110 '
b11001010000110111101010010010100 $
b11001010000110111101010010010100 )
b1001010000110111101001011001100 &
#325000
0!
0.
b11100001101000101101111111000011 +
1#
b110011001001010100101101100110 %
b110011001001010100101101100110 *
b10110011001001010100100010001111 '
b10100110010000010101100101001 $
b10100110010000010101100101001 )
b10010100110010000010100101011101 &
#330000
1!
1.
b11010101101001100111101110101011 +
0,
b100010000110010101111101000100 %
b100010000110010101111101000100 *
b10100010000110010101110110000100 '
b11110111101111111101101011101111 $
b11110111101111111101101011101111 )
b1110111101111111101100001111010 &
#335000
0!
0.
b101100001001111010000001011 +
0#
b11110101100100111001100011101011 %
b11110101100100111001100011101011 *
b1110101100100111001011010110101 '
b11111011000110001000110011110110 $
b11111011000110001000110011110110 )
b1111011000110001000101110110011 &
#340000
1!
1.
b100000111001110001011001000001 +
0,
1#
b10111100100010111110000001111001 %
b10111100100010111110000001111001 *
b111100100010111101111111110010 '
b11011101011100101111011010111010 $
b11011101011100101111011010111010 )
b1011101011100101111010101011000 &
#345000
0!
0.
b101010100010000101000001010101 +
1,
0#
b11110110010100111010000011101100 %
b11110110010100111010000011101100 *
b1110110010100111001111011001011 '
b100000110110111111000101000001 $
b100000110110111111000101000001 )
b10100000110110111110111101111001 &
#350000
1!
1.
0,
b1001011111011110111001010011000 +
1#
b11110110100010111100100111101 %
b11110110100010111100100111101 *
b10011110110100010111011110010000 '
b1101010110000001110101111010101 $
b1101010110000001110101111010101 )
b11101010110000001110100011100110 &
#355000
0!
0.
1,
b1101000110101010010000011010010 +
b11001000010111110001000010010000 %
b11001000010111110001000010010000 *
b1001000010111110000111001010001 '
b110001001101000011000101100010 $
b110001001101000011000101100010 )
b10110001001101000010111000101111 &
#360000
b11100101001001101100101111001010 +
b1010110001010011001010110101100 %
b1010110001010011001010110101100 *
b11010110001010011001001111011110 '
b111011010100000110000101110110 $
b111011010100000110000101110110 )
b10111011010100000101111010100100 &
#365000
1!
1.
b1000011001000100110111010000110 +
0,
b10101111101010111011000001011111 %
b10101111101010111011000001011111 *
b101111101010111010111011000111 '
b11110010110011100001111011100101 $
b11110010110011100001111011100101 )
b1110010110011100001110101010101 &
#370000
0!
0.
b11110000101111011011110111100001 +
1,
b10011001000100001001100100110 %
b10011001000100001001100100110 *
b10010011001000100001000001011100 '
b11110111111101000100000111 $
b11110111111101000100000111 )
b10000011110111111100111000010010 &
#375000
1!
1.
b101000010010010010101001010001 +
0,
b11101011101111100011100111010 %
b11101011101111100011100111010 *
b10011101011101111100010110101101 '
b1000101110000001111000110001011 $
b1000101110000001111000110001011 )
b11000101110000001110111001101011 &
#380000
1(
b100010011001010100010001000101 +
b1110011101000000001011111100111 %
b1110011101000000001011111100111 *
b11110011101000000001010010001010 '
b10010110000001010101110000101100 $
b10010110000001010101110000101100 )
b10110000001010101101010110000 &
#385000
0!
0.
0(
1,
b11110101110011110001100111101100 +
b11001100110001010111011010011001 %
b11001100110001010111011010011001 *
b1001100110001010111010010000011 '
b11000010100101001001000010000101 $
b11000010100101001001000010000101 )
b1000010100101001000111011110001 &
#390000
1!
1.
1(
b1110101100111011011111011101011 +
0,
0#
b1110101100010111111010111101011 %
b1110101100010111111010111101011 *
b11110101100010111111001111101000 '
b11101011001010011011010011010110 $
b11101011001010011011010011010110 )
b1101011001010011011001111111110 &
#395000
0(
1!
1.
b11110010001010011110111111100101 +
1,
b110000010111010001101101100000 %
b110000010111010001101101100000 *
b10110000010111010001100011001001 '
b100010100001110000101101000101 $
b100010100001110000101101000101 )
b10100010100001110000100001100111 &
#400000
1!
1.
b11111100010111011110011111111000 +
1,
b10001101100110000000111000011011 %
b10001101100110000000111000011011 *
b1101100110000000110111110110 '
b10001001111101011111011000010011 $
b10001001111101011111011000010011 )
b1001111101011111010101111100 &
#405000
0(
1!
1.
b11000011011110100011010110000111 +
0,
b101001011011101010110101010010 %
b101001011011101010110101010010 *
b10101001011011101010101111111111 '
b11101100111010001110001011011001 $
b11101100111010001110001011011001 )
b1101100111010001110000001001101 &
#410000
0!
0.
1,
b11110001110100011101011111100100 +
1#
b1111000010110101011000111110000 %
b1111000010110101011000111110000 *
b11111000010110101010111000110100 '
b1101010001011001000100111010100 $
b1101010001011001000100111010100 )
b11101010001011001000011010101010 &
#415000
b100101011111100101011001001011 +
0,
0#
b10101001101010100010010001010011 %
b10101001101010100010010001010011 *
b101001101010100010001110100101 '
b11001111001010000111101010011110 $
b11001111001010000111101010011110 )
b1001111001010000111100000100011 &
#420000
1(
0!
0.
b11000100111100100000111110001010 +
1,
b10100100101100101110111001001001 %
b10100100101100101110111001001001 *
b100100101100101110110000100010 '
b1101001101001001111110111010011 $
b1101001101001001111110111010011 )
b11101001101001001111101100001000 &
#425000
0(
0!
0.
b1111011111011001110000011111 +
0,
b11100101011001101101001011001010 %
b11100101011001101101001011001010 *
b1100101011001101101000100111011 '
b11110100111001000110111011101001 $
b11110100111001000110111011101001 )
b1110100111001000110110101101001 &
#430000
b1100100101100100110100011001001 +
1,
b10111101001100001000110001111010 %
b10111101001100001000110001111010 *
b111101001100001000101101000000 '
b100001111000101111010101000011 $
b100001111000101111010101000011 )
b10100001111000101111001000010110 &
#435000
1!
1.
0,
b11000111010110011011000110010 +
1#
b10000010001100011100010000000100 %
b10000010001100011100010000000100 *
b10001100011100001001000001 '
b10011011000111001111101000110110 $
b10011011000111001111101000110110 )
b11011000111001111100110011111 &
#440000
b11101100010010001110000111011 +
b10001010111101101101110000010101 %
b10001010111101101101110000010101 *
b1010111101101101101100001110 '
b10101000011111111111100001010000 $
b10101000011111111111100001010000 )
b101000011111111111011101010100 &
#445000
0!
0.
1(
b10111001100000010011001101110011 +
1,
0#
b10101011110110110010001001010111 %
b10101011110110110010001001010111 *
b101011110110110010000000110111 '
b1100101010111000101010111001010 $
b1100101010111000101010111001010 )
b11100101010111000101001001000101 &
#450000
0(
b1001110000011011100110010011100 +
1#
b11011111010100101001100010111110 %
b11011111010100101001100010111110 *
b1011111010100101001011100001100 '
b101101011000000110010101011010 $
b101101011000000110010101011010 )
b10101101011000000110001001000010 &
#455000
1!
1.
b11111111100100110111011111111111 +
0#
b10011101110110101001001000111011 %
b10011101110110101001001000111011 *
b11101110110101001000010011101 '
b10011101011011100000101000111010 $
b10011101011011100000101000111010 )
b11101011011100000100011011011 &
#460000
0(
b10011110011100000110111100111101 +
0,
1#
b10001111110101100100100100011 %
b10001111110101100100100100011 *
b10010001111110101100011010111010 '
b10110000011010110011100001100000 $
b10110000011010110011100001100000 )
b110000011010110011011001100000 &
#465000
b101010110101101011000001010 +
b11101000101000101001011011010001 %
b11101000101000101001011011010001 *
b1101000101000101001010011110011 '
b11101101111111010110110011011011 $
b11101101111111010110110011011011 )
b1101101111111010110101011100001 &
#470000
b10111100100010000110010101111001 +
0,
0#
b100000101101001001111101000001 %
b100000101101001001111101000001 *
b10100000101101001001110110011000 '
b11011101001111010000010010111010 $
b11011101001111010000010010111010 )
b1011101001111010000001100101110 &
#475000
0!
0.
0(
1,
b1001011111101111111011010011000 +
1#
b11111010001110101110110011110100 %
b11111010001110101110110011110100 *
b1111010001110101110101010111001 '
b1000110001100101110001110001100 $
b1000110001100101110001110001100 )
b11000110001100101110000111010111 &
#480000
1!
1.
1(
0,
b1100100001110110110100011001001 +
b1001001110100100101110110010011 %
b1001001110100100101110110010011 *
b11001001110100100101101100100110 '
b10101110000011011100011001011100 $
b10101110000011011100011001011100 )
b101110000011011100010000101100 &
#485000
0(
b10110000111011100110011101100010 +
b100111001110011110110101001110 %
b100111001110011110110101001110 *
b10100111001110011110101101101111 '
b11011000001010000101010010110000 $
b11011000001010000101010010110000 )
b1011000001010000101001100111101 &
#490000
0!
0.
b110001111111001001011001100100 +
0#
b1000101110001010010110110001011 %
b1000101110001010010110110001011 *
b11000101110001010010101011100100 '
b1110111110000011100001111101111 $
b1110111110000011100001111101111 )
b11110111110000011100000011011010 &
#495000
1!
1.
b1110000110101111001010011100010 +
1#
b1100111101001110111100011001 %
b1100111101001110111100011001 *
b10001100111101001110110010010101 '
b1111101110011001000001111111011 $
b1111101110011001000001111111011 )
b11111101110011001000000010010011 &
#500000
1,
b11100011001000110110011111000110 +
0#
b10111100101110100000011001111001 %
b10111100101110100000011001111001 *
b111100101110100000010001010010 '
b10011111110111010110111000111111 $
b10011111110111010110111000111111 )
b11111110111010110110010111000 &
#505000
0,
1!
1.
b11000000011011100100000110001 +
1#
b10010111011111111010000000101110 %
b10010111011111111010000000101110 *
b10111011111111001111110101011 '
b10101111100011010110100001011111 $
b10101111100011010110100001011111 )
b101111100011010110011101011001 &
#510000
0!
0.
b10111101110110101011101101111100 +
1,
b1101011111110011000110111010111 %
b1101011111110011000110111010111 *
b11101011111110011000101011110000 '
b101001110101000100100101010011 $
b101001110101000100100101010011 )
b10101001110101000100011101000110 &
#515000
1!
1.
b11100000000011110010110111000000 +
1,
0#
b10101101110100100111010001011011 %
b10101101110100100111010001011011 *
b101101110100100111001000110001 '
b10001101111000011010001000011011 $
b10001101111000011010001000011011 )
b1101111000011010000100001111 &
#520000
1(
b1100000011001111100110011000000 +
0,
1#
b1010011100000101111000110100111 %
b1010011100000101111000110100111 *
b11010011100000101110111000111110 '
b10110011111010101011111001100111 $
b10110011111010101011111001100111 )
b110011111010101011110000000100 &
#525000
b1000110010110001101010010001101 +
b1110100001011111110111111101000 %
b1110100001011111110111111101000 *
b11110100001011111110110110100111 '
b10111010100010001100010001110101 $
b10111010100010001100010001110101 )
b111010100010001100001100110101 &
#530000
0(
1!
1.
b10101101100010010011100101011011 +
1,
0#
b1100111000110011100101111001110 %
b1100111000110011100101111001110 *
b11100111000110011100100110111100 '
b10100101000110000010100101001 $
b10100101000110000010100101001 )
b10010100101000110000001001110010 &
#535000
0!
0.
b100111011110011010100001001111 +
0,
b10101000101000010001100001010001 %
b10101000101000010001100001010001 *
b101000101000010001011110001101 '
b11010000000110101100000010100000 $
b11010000000110101100000010100000 )
b1010000000110101011111101001011 &
#540000
1!
1.
1(
b1110001101011011111100011100011 +
b1001110101111110000011110011101 %
b1001110101111110000011110011101 *
b11001110101111110000010011101010 '
b11000000011011010000000010000000 $
b11000000011011010000000010000000 )
b1000000011011001111111000010000 &
#545000
0!
0.
0(
1,
b11010111000111010111000110101110 +
1#
b11000111001000001101001010001110 %
b11000111001000001101001010001110 *
b1000111001000001101000101100011 '
b10011110001111100100010000111100 $
b10011110001111100100010000111100 )
b11110001111100100001011010001 &
#550000
0!
0.
0(
b110010110001000110110001100110 +
0#
b11110001010011001011010011100010 %
b11110001010011001011010011100010 *
b1110001010011001011001101001000 '
b100100000100010010000101001000 $
b100100000100010010000101001000 )
b10100100000100010001111001011110 &
#555000
1!
1.
0,
b1011110011111101111000011000 +
1#
b11010010110011100011101010100101 %
b11010010110011100011101010100101 *
b1010010110011100011100010101001 '
b11011110100111100001100010111101 $
b11011110100111100001100010111101 )
b1011110100111100001011101000111 &
#560000
0!
0.
1(
b11100010011000010100101111000101 +
1,
0#
b10000000101011001111011000000001 %
b10000000101011001111011000000001 *
b101011001111010001010110 '
b1100011000011100100000111000110 $
b1100011000011100100000111000110 )
b11100011000011100011111011011100 &
#565000
b10000011001101110111110100000110 +
b11000111001111100000100010001110 %
b11000111001111100000100010001110 *
b1000111001111100000011011011111 '
b1001010011101011000010110010100 $
b1001010011101011000010110010100 )
b11001010011101011000001000101101 &
#570000
0(
0!
0.
b1011111111111101011010011000000 +
b10111001111000111101010001110011 %
b10111001111000111101010001110011 *
b111001111000111101001110010100 '
b11001111000101000100100110011 $
b11001111000101000100100110011 )
b10011001111000101000011100001010 &
#575000
1!
1.
0(
b10000001100010001011001100000011 +
0,
b1000000110000101111001110000001 %
b1000000110000101111001110000001 *
b11000000110000101111000110000101 '
b11000010010010111010011010000100 $
b11000010010010111010011010000100 )
b1000010010010111010010100000011 &
#580000
0(
0!
0.
b1011111000100110010001010111110 +
1,
1#
b10110011111001000010101001100111 %
b10110011111001000010101001100111 *
b110011111001000010100010000010 '
b10010111101110100110100100101 $
b10010111101110100110100100101 )
b10010010111101110100101001101000 &
